{"version": 7,
 "packagesDir": ".lake/packages",
 "packages":
 [{"url": "https://github.com/leanprover/std4.git",
   "type": "git",
   "subDir": null,
   "rev": "276953b13323ca151939eafaaec9129bf7970306",
   "name": "std",
   "manifestFile": "lake-manifest.json",
   "inputRev": "v4.6.0-rc1",
   "inherited": true,
   "configFile": "lakefile.lean"},
  {"url": "https://github.com/leanprover-community/lean-auto.git",
   "type": "git",
   "subDir": null,
   "rev": "b53593923a1423ae145c47c66306a68b6d0fbf44",
   "name": "auto",
   "manifestFile": "lake-manifest.json",
   "inputRev": "v0.0.6",
   "inherited": false,
   "configFile": "lakefile.lean"}],
 "name": "Duper",
 "lakeDir": ".lake"}
